wpp/__init__.py
wpp-0.0.0.dist-info/LICENSE
wpp-0.0.0.dist-info/METADATA
wpp-0.0.0.dist-info/WHEEL
wpp-0.0.0.dist-info/top_level.txt
wpp-0.0.0.dist-info/RECORD
